{
  "version": 1,
  "serviceConfiguration": {
    "serviceName": "AppSync",
    "defaultAuthType": {
      "mode": "AWS_LAMBDA",
      "lambdaFunction": "graphQlLambdaAuthorizer226fb5bc",
      "ttlSeconds": "900"
    },
    "conflictResolution": {
      "defaultResolutionStrategy": {
        "type": "AUTOMERGE"
      }
    },
    "apiName": "amplifyDatasource",
    "gqlSchemaPath": "C:\\Users\\Shamikh Qu\\AndroidStudioProjects\\sham1\\taskmaster\\amplify\\backend\\api\\amplifyDatasource\\schema.graphql",
    "additionalAuthTypes": []
  }
}